cxhs/__init__.py
cxhs/auth.py
cxhs/client.py
cxhs/core.py
cxhs/filter.py
cxhs/grid.py
cxhs/io.py
cxhs/scram.py
cxhs/session.py
cxhs/val.py
cxhs-1.2.6.dist-info/LICENSE
cxhs-1.2.6.dist-info/METADATA
cxhs-1.2.6.dist-info/WHEEL
cxhs-1.2.6.dist-info/top_level.txt
cxhs-1.2.6.dist-info/RECORD
