Metadata-Version: 2.1
Name: cxhs
Version: 1.2.6
Summary: cxhs: A Python Haystack client
Home-page: http://www.connexxenergy.com/
Author: Connexx Energy
Author-email: connexxion@connexxenergy.com
Maintainer: Connexx Energy
Maintainer-email: connexxion@connexxenergy.com
License: Apache License, Version 2.0
Platform: any
License-File: LICENSE
